LICENSE
MANIFEST.in
README.md
package.json
setup.py
dash_trich_components/Card.py
dash_trich_components/Carousel.py
dash_trich_components/GridItem.py
dash_trich_components/GridLayoutComponent.py
dash_trich_components/ResponsiveGrid.py
dash_trich_components/SideBar.py
dash_trich_components/SideBarItem.py
dash_trich_components/SideBarToggle.py
dash_trich_components/ThemeToggle.py
dash_trich_components/__init__.py
dash_trich_components/_imports_.py
dash_trich_components/dash_trich_components.min.js
dash_trich_components/dash_trich_components.min.js.map
dash_trich_components/metadata.json
dash_trich_components/package-info.json
dash_trich_components.egg-info/PKG-INFO
dash_trich_components.egg-info/SOURCES.txt
dash_trich_components.egg-info/dependency_links.txt
dash_trich_components.egg-info/top_level.txt