Metadata-Version: 2.1
Name: dash-trich-components
Version: 1.0.0
Summary: Trich.ai components library for Dash Plotly
Home-page: UNKNOWN
Author: Natacha Romano <natacharomanonr@gmail.com>
License: MIT
Platform: UNKNOWN
Classifier: Framework :: Dash
